impart/__init__.py
impart/image_partition.py
impart-0.0.5.dist-info/METADATA
impart-0.0.5.dist-info/WHEEL
impart-0.0.5.dist-info/licenses/LICENSE
impart-0.0.5.dist-info/RECORD
