Metadata-Version: 2.3
Name: impart
Version: 0.0.5
Summary: Partition images and volumes of arbitrary size
Project-URL: Homepage, https://gitlab.com/hcording/impart
Project-URL: Bug Tracker, https://gitlab.com/hcording/impart/-/issues
Author-email: "Henry M. Cording" <umzqa92b@duck.com>
License-File: LICENSE
Classifier: License :: OSI Approved :: MIT License
Classifier: Operating System :: OS Independent
Classifier: Programming Language :: Python :: 3
Requires-Python: >=3.10
Requires-Dist: numpy
Requires-Dist: pyvips
